[
    {
        "id": 3498,
        "name": "Grand Theft Auto V",
        "genres": [
            {
                "id": 4,
                "name": "Action",
                "slug": "action",
                "games_count": 134093,
                "image_background": "https://media.rawg.io/media/games/c4b/c4b0cab189e73432de3a250d8cf1c84e.jpg"
            },
            {
                "id": 3,
                "name": "Adventure",
                "slug": "adventure",
                "games_count": 99466,
                "image_background": "https://media.rawg.io/media/games/26d/26d4437715bee60138dab4a7c8c59c92.jpg"
            }
        ],
        "image": "Grand_Theft.jpg",
        "rating": 4.48,
        "platforms": [
            "PlayStation 5",
            "PlayStation 4",
            "PlayStation 3",
            "Xbox 360",
            "PC",
            "Xbox One",
            "Xbox Series S/X"
        ]
    },
    {
        "id": 3328,
        "name": "The Witcher 3: Wild Hunt",
        "genres": [
            {
                "id": 4,
                "name": "Action",
                "slug": "action",
                "games_count": 134093,
                "image_background": "https://media.rawg.io/media/games/c4b/c4b0cab189e73432de3a250d8cf1c84e.jpg"
            },
            {
                "id": 3,
                "name": "Adventure",
                "slug": "adventure",
                "games_count": 99466,
                "image_background": "https://media.rawg.io/media/games/26d/26d4437715bee60138dab4a7c8c59c92.jpg"
            },
            {
                "id": 5,
                "name": "RPG",
                "slug": "role-playing-games-rpg",
                "games_count": 40860,
                "image_background": "https://media.rawg.io/media/games/d82/d82990b9c67ba0d2d09d4e6fa88885a7.jpg"
            }
        ],
        "image": "The_Witcher.jpg",
        "rating": 4.67,
        "platforms": [
            "Nintendo Switch",
            "Xbox One",
            "PC",
            "PlayStation 4"
        ]
    },
    {
        "id": 4200,
        "name": "Portal 2",
        "genres": [
            {
                "id": 2,
                "name": "Shooter",
                "slug": "shooter",
                "games_count": 45301,
                "image_background": "https://media.rawg.io/media/games/7a2/7a2500ee8b2c0e1ff268bb4479463dea.jpg"
            },
            {
                "id": 7,
                "name": "Puzzle",
                "slug": "puzzle",
                "games_count": 75573,
                "image_background": "https://media.rawg.io/media/games/2e1/2e187b31e5cee21c110bd16798d75fab.jpg"
            }
        ],
        "image": "Portal_2.jpg",
        "rating": 4.62,
        "platforms": [
            "Xbox 360",
            "macOS",
            "Linux",
            "PC",
            "PlayStation 3",
            "Xbox One"
        ]
    },
    {
        "id": 5286,
        "name": "Tomb Raider (2013)",
        "genres": [
            {
                "id": 4,
                "name": "Action",
                "slug": "action",
                "games_count": 134093,
                "image_background": "https://media.rawg.io/media/games/c4b/c4b0cab189e73432de3a250d8cf1c84e.jpg"
            },
            {
                "id": 3,
                "name": "Adventure",
                "slug": "adventure",
                "games_count": 99466,
                "image_background": "https://media.rawg.io/media/games/26d/26d4437715bee60138dab4a7c8c59c92.jpg"
            }
        ],
        "image": "Tomb_Raider.jpg",
        "rating": 4.06,
        "platforms": [
            "macOS",
            "Xbox One",
            "PlayStation 4",
            "PC",
            "Xbox 360",
            "PlayStation 3"
        ]
    },
    {
        "id": 5679,
        "name": "The Elder Scrolls V: Skyrim",
        "genres": [
            {
                "id": 4,
                "name": "Action",
                "slug": "action",
                "games_count": 134093,
                "image_background": "https://media.rawg.io/media/games/c4b/c4b0cab189e73432de3a250d8cf1c84e.jpg"
            },
            {
                "id": 5,
                "name": "RPG",
                "slug": "role-playing-games-rpg",
                "games_count": 40860,
                "image_background": "https://media.rawg.io/media/games/d82/d82990b9c67ba0d2d09d4e6fa88885a7.jpg"
            }
        ],
        "image": "The_Elder.jpg",
        "rating": 4.42,
        "platforms": [
            "PC",
            "Nintendo Switch",
            "Xbox 360",
            "PlayStation 3"
        ]
    },
    {
        "id": 12020,
        "name": "Left 4 Dead 2",
        "genres": [
            {
                "id": 4,
                "name": "Action",
                "slug": "action",
                "games_count": 134093,
                "image_background": "https://media.rawg.io/media/games/c4b/c4b0cab189e73432de3a250d8cf1c84e.jpg"
            },
            {
                "id": 2,
                "name": "Shooter",
                "slug": "shooter",
                "games_count": 45301,
                "image_background": "https://media.rawg.io/media/games/7a2/7a2500ee8b2c0e1ff268bb4479463dea.jpg"
            }
        ],
        "image": "Left_4.jpg",
        "rating": 4.09,
        "platforms": [
            "Xbox 360",
            "PC",
            "macOS",
            "Linux"
        ]
    },
    {
        "id": 4291,
        "name": "Counter-Strike: Global Offensive",
        "genres": [
            {
                "id": 4,
                "name": "Action",
                "slug": "action",
                "games_count": 134093,
                "image_background": "https://media.rawg.io/media/games/c4b/c4b0cab189e73432de3a250d8cf1c84e.jpg"
            },
            {
                "id": 2,
                "name": "Shooter",
                "slug": "shooter",
                "games_count": 45301,
                "image_background": "https://media.rawg.io/media/games/7a2/7a2500ee8b2c0e1ff268bb4479463dea.jpg"
            }
        ],
        "image": "Counter_Strike.jpg",
        "rating": 3.58,
        "platforms": [
            "PC",
            "Xbox 360",
            "PlayStation 3"
        ]
    },
    {
        "id": 13536,
        "name": "Portal",
        "genres": [
            {
                "id": 3,
                "name": "Adventure",
                "slug": "adventure",
                "games_count": 99466,
                "image_background": "https://media.rawg.io/media/games/26d/26d4437715bee60138dab4a7c8c59c92.jpg"
            },
            {
                "id": 7,
                "name": "Puzzle",
                "slug": "puzzle",
                "games_count": 75573,
                "image_background": "https://media.rawg.io/media/games/2e1/2e187b31e5cee21c110bd16798d75fab.jpg"
            }
        ],
        "image": "Portal.jpg",
        "rating": 4.51,
        "platforms": [
            "Android",
            "PlayStation 3",
            "Xbox 360",
            "Linux",
            "macOS",
            "PC"
        ]
    },
    {
        "id": 4062,
        "name": "BioShock Infinite",
        "genres": [
            {
                "id": 4,
                "name": "Action",
                "slug": "action",
                "games_count": 134093,
                "image_background": "https://media.rawg.io/media/games/c4b/c4b0cab189e73432de3a250d8cf1c84e.jpg"
            },
            {
                "id": 2,
                "name": "Shooter",
                "slug": "shooter",
                "games_count": 45301,
                "image_background": "https://media.rawg.io/media/games/7a2/7a2500ee8b2c0e1ff268bb4479463dea.jpg"
            }
        ],
        "image": "BioShock_Infinite.jpg",
        "rating": 4.39,
        "platforms": [
            "Xbox 360",
            "Nintendo Switch",
            "PC",
            "Linux",
            "PlayStation 3",
            "PlayStation 4",
            "Xbox One"
        ]
    },
    {
        "id": 802,
        "name": "Borderlands 2",
        "genres": [
            {
                "id": 4,
                "name": "Action",
                "slug": "action",
                "games_count": 134093,
                "image_background": "https://media.rawg.io/media/games/c4b/c4b0cab189e73432de3a250d8cf1c84e.jpg"
            },
            {
                "id": 2,
                "name": "Shooter",
                "slug": "shooter",
                "games_count": 45301,
                "image_background": "https://media.rawg.io/media/games/7a2/7a2500ee8b2c0e1ff268bb4479463dea.jpg"
            },
            {
                "id": 5,
                "name": "RPG",
                "slug": "role-playing-games-rpg",
                "games_count": 40860,
                "image_background": "https://media.rawg.io/media/games/d82/d82990b9c67ba0d2d09d4e6fa88885a7.jpg"
            }
        ],
        "image": "Borderlands_2.jpg",
        "rating": 4.04,
        "platforms": [
            "PlayStation 4",
            "Xbox 360",
            "PlayStation 3",
            "PC",
            "Xbox One",
            "macOS"
        ]
    },
    {
        "id": 3439,
        "name": "Life is Strange",
        "genres": [
            {
                "id": 3,
                "name": "Adventure",
                "slug": "adventure",
                "games_count": 99466,
                "image_background": "https://media.rawg.io/media/games/26d/26d4437715bee60138dab4a7c8c59c92.jpg"
            }
        ],
        "image": "Life_is.jpg",
        "rating": 4.11,
        "platforms": [
            "PC",
            "Linux",
            "PlayStation 3",
            "macOS",
            "iOS",
            "Xbox 360",
            "Android",
            "PlayStation 4",
            "Xbox One"
        ]
    },
    {
        "id": 28,
        "name": "Red Dead Redemption 2",
        "genres": [
            {
                "id": 4,
                "name": "Action",
                "slug": "action",
                "games_count": 134093,
                "image_background": "https://media.rawg.io/media/games/c4b/c4b0cab189e73432de3a250d8cf1c84e.jpg"
            },
            {
                "id": 3,
                "name": "Adventure",
                "slug": "adventure",
                "games_count": 99466,
                "image_background": "https://media.rawg.io/media/games/26d/26d4437715bee60138dab4a7c8c59c92.jpg"
            }
        ],
        "image": "Red_Dead.jpg",
        "rating": 4.58,
        "platforms": [
            "Xbox One",
            "PC",
            "PlayStation 4"
        ]
    },
    {
        "id": 4286,
        "name": "BioShock",
        "genres": [
            {
                "id": 4,
                "name": "Action",
                "slug": "action",
                "games_count": 134093,
                "image_background": "https://media.rawg.io/media/games/c4b/c4b0cab189e73432de3a250d8cf1c84e.jpg"
            },
            {
                "id": 2,
                "name": "Shooter",
                "slug": "shooter",
                "games_count": 45301,
                "image_background": "https://media.rawg.io/media/games/7a2/7a2500ee8b2c0e1ff268bb4479463dea.jpg"
            }
        ],
        "image": "BioShock.jpg",
        "rating": 4.38,
        "platforms": [
            "Xbox 360",
            "PlayStation 3",
            "iOS",
            "macOS",
            "PlayStation 4",
            "PC",
            "Xbox One"
        ]
    },
    {
        "id": 13537,
        "name": "Half-Life 2",
        "genres": [
            {
                "id": 4,
                "name": "Action",
                "slug": "action",
                "games_count": 134093,
                "image_background": "https://media.rawg.io/media/games/c4b/c4b0cab189e73432de3a250d8cf1c84e.jpg"
            },
            {
                "id": 2,
                "name": "Shooter",
                "slug": "shooter",
                "games_count": 45301,
                "image_background": "https://media.rawg.io/media/games/7a2/7a2500ee8b2c0e1ff268bb4479463dea.jpg"
            }
        ],
        "image": "Half_Life_2.jpg",
        "rating": 4.49,
        "platforms": [
            "PC",
            "Xbox 360",
            "Linux",
            "Xbox",
            "Android",
            "macOS"
        ]
    },
    {
        "id": 1030,
        "name": "Limbo",
        "genres": [
            {
                "id": 3,
                "name": "Adventure",
                "slug": "adventure",
                "games_count": 99466,
                "image_background": "https://media.rawg.io/media/games/26d/26d4437715bee60138dab4a7c8c59c92.jpg"
            },
            {
                "id": 51,
                "name": "Indie",
                "slug": "indie",
                "games_count": 40791,
                "image_background": "https://media.rawg.io/media/games/dd5/dd50d4266915d56dd5b63ae1bf72606a.jpg"
            },
            {
                "id": 7,
                "name": "Puzzle",
                "slug": "puzzle",
                "games_count": 75573,
                "image_background": "https://media.rawg.io/media/games/2e1/2e187b31e5cee21c110bd16798d75fab.jpg"
            },
            {
                "id": 83,
                "name": "Platformer",
                "slug": "platformer",
                "games_count": 73872,
                "image_background": "https://media.rawg.io/media/games/8a0/8a02f84a5916ede2f923b88d5f8217ba.jpg"
            }
        ],
        "image": "Limbo.jpg",
        "rating": 4.17,
        "platforms": [
            "PlayStation 4",
            "PlayStation 3",
            "Xbox 360",
            "macOS",
            "PC",
            "iOS",
            "Android",
            "PS Vita",
            "Nintendo Switch",
            "Linux",
            "Xbox One"
        ]
    },
    {
        "id": 2454,
        "name": "DOOM (2016)",
        "genres": [
            {
                "id": 4,
                "name": "Action",
                "slug": "action",
                "games_count": 134093,
                "image_background": "https://media.rawg.io/media/games/c4b/c4b0cab189e73432de3a250d8cf1c84e.jpg"
            },
            {
                "id": 2,
                "name": "Shooter",
                "slug": "shooter",
                "games_count": 45301,
                "image_background": "https://media.rawg.io/media/games/7a2/7a2500ee8b2c0e1ff268bb4479463dea.jpg"
            }
        ],
        "image": "DOOM.jpg",
        "rating": 4.39,
        "platforms": [
            "PlayStation 4",
            "Nintendo Switch",
            "PC",
            "Xbox One"
        ]
    },
    {
        "id": 3070,
        "name": "Fallout 4",
        "genres": [
            {
                "id": 4,
                "name": "Action",
                "slug": "action",
                "games_count": 134093,
                "image_background": "https://media.rawg.io/media/games/c4b/c4b0cab189e73432de3a250d8cf1c84e.jpg"
            },
            {
                "id": 5,
                "name": "RPG",
                "slug": "role-playing-games-rpg",
                "games_count": 40860,
                "image_background": "https://media.rawg.io/media/games/d82/d82990b9c67ba0d2d09d4e6fa88885a7.jpg"
            }
        ],
        "image": "Fallout_4.jpg",
        "rating": 3.77,
        "platforms": [
            "PlayStation 4",
            "PC",
            "Xbox One"
        ]
    },
    {
        "id": 11859,
        "name": "Team Fortress 2",
        "genres": [
            {
                "id": 4,
                "name": "Action",
                "slug": "action",
                "games_count": 134093,
                "image_background": "https://media.rawg.io/media/games/c4b/c4b0cab189e73432de3a250d8cf1c84e.jpg"
            },
            {
                "id": 2,
                "name": "Shooter",
                "slug": "shooter",
                "games_count": 45301,
                "image_background": "https://media.rawg.io/media/games/7a2/7a2500ee8b2c0e1ff268bb4479463dea.jpg"
            }
        ],
        "image": "Team_Fortress_2.jpg",
        "rating": 3.68,
        "platforms": [
            "Linux",
            "macOS",
            "PC"
        ]
    },
    {
        "id": 32,
        "name": "Destiny 2",
        "genres": [
            {
                "id": 4,
                "name": "Action",
                "slug": "action",
                "games_count": 134093,
                "image_background": "https://media.rawg.io/media/games/c4b/c4b0cab189e73432de3a250d8cf1c84e.jpg"
            },
            {
                "id": 2,
                "name": "Shooter",
                "slug": "shooter",
                "games_count": 45301,
                "image_background": "https://media.rawg.io/media/games/7a2/7a2500ee8b2c0e1ff268bb4479463dea.jpg"
            },
            {
                "id": 3,
                "name": "Adventure",
                "slug": "adventure",
                "games_count": 99466,
                "image_background": "https://media.rawg.io/media/games/26d/26d4437715bee60138dab4a7c8c59c92.jpg"
            },
            {
                "id": 59,
                "name": "Massively Multiplayer",
                "slug": "massively-multiplayer",
                "games_count": 2655,
                "image_background": "https://media.rawg.io/media/games/11f/11fd681c312c14644ab360888dba3486.jpg"
            }
        ],
        "image": "Destiny_2.jpg",
        "rating": 3.59,
        "platforms": [
            "Xbox One",
            "PC",
            "PlayStation 4",
            "Web",
            "Xbox Series S/X",
            "PlayStation 5"
        ]
    },
    {
        "id": 3939,
        "name": "PAYDAY 2",
        "genres": [
            {
                "id": 4,
                "name": "Action",
                "slug": "action",
                "games_count": 134093,
                "image_background": "https://media.rawg.io/media/games/c4b/c4b0cab189e73432de3a250d8cf1c84e.jpg"
            },
            {
                "id": 2,
                "name": "Shooter",
                "slug": "shooter",
                "games_count": 45301,
                "image_background": "https://media.rawg.io/media/games/7a2/7a2500ee8b2c0e1ff268bb4479463dea.jpg"
            }
        ],
        "image": "PAYDAY_2.jpg",
        "rating": 3.5,
        "platforms": [
            "Linux",
            "PC",
            "Xbox One"
        ]
    },
    {
        "id": 4459,
        "name": "Grand Theft Auto IV",
        "genres": [
            {
                "id": 4,
                "name": "Action",
                "slug": "action",
                "games_count": 134093,
                "image_background": "https://media.rawg.io/media/games/c4b/c4b0cab189e73432de3a250d8cf1c84e.jpg"
            },
            {
                "id": 3,
                "name": "Adventure",
                "slug": "adventure",
                "games_count": 99466,
                "image_background": "https://media.rawg.io/media/games/26d/26d4437715bee60138dab4a7c8c59c92.jpg"
            }
        ],
        "image": "Grand_Theft_V.jpg",
        "rating": 4.25,
        "platforms": [
            "Xbox 360",
            "PlayStation 3",
            "Xbox One",
            "PC"
        ]
    },
    {
        "id": 3272,
        "name": "Rocket League",
        "genres": [
            {
                "id": 15,
                "name": "Sports",
                "slug": "sports",
                "games_count": 17962,
                "image_background": "https://media.rawg.io/media/games/082/082365507ff04d456c700157072d35db.jpg"
            },
            {
                "id": 1,
                "name": "Racing",
                "slug": "racing",
                "games_count": 20061,
                "image_background": "https://media.rawg.io/media/games/19a/19a512a8c1293c22894b7364e1405ec1.jpg"
            },
            {
                "id": 51,
                "name": "Indie",
                "slug": "indie",
                "games_count": 40791,
                "image_background": "https://media.rawg.io/media/games/dd5/dd50d4266915d56dd5b63ae1bf72606a.jpg"
            }
        ],
        "image": "Rocket League.jpg",
        "rating": 3.99,
        "platforms": [
            "Nintendo Switch",
            "Linux",
            "macOS",
            "PC",
            "Xbox One",
            "PlayStation 4"
        ]
    },
    {
        "id": 278,
        "name": "Horizon Zero Dawn",
        "genres": [
            {
                "id": 4,
                "name": "Action",
                "slug": "action",
                "games_count": 134093,
                "image_background": "https://media.rawg.io/media/games/c4b/c4b0cab189e73432de3a250d8cf1c84e.jpg"
            },
            {
                "id": 3,
                "name": "Adventure",
                "slug": "adventure",
                "games_count": 99466,
                "image_background": "https://media.rawg.io/media/games/26d/26d4437715bee60138dab4a7c8c59c92.jpg"
            },
            {
                "id": 5,
                "name": "RPG",
                "slug": "role-playing-games-rpg",
                "games_count": 40860,
                "image_background": "https://media.rawg.io/media/games/d82/d82990b9c67ba0d2d09d4e6fa88885a7.jpg"
            }
        ],
        "image": "Horizon_Zero_Dawn.jpg",
        "rating": 4.34,
        "platforms": [
            "PlayStation 4",
            "PC"
        ]
    },
    {
        "id": 58175,
        "name": "God of War",
        "genres": [
            {
                "id": 4,
                "name": "Action",
                "slug": "action",
                "games_count": 134351,
                "image_background": "https://media.rawg.io/media/games/f87/f87457e8347484033cb34cde6101d08d.jpg"
            },
            {
                "id": 3,
                "name": "Adventure",
                "slug": "adventure",
                "games_count": 99679,
                "image_background": "https://media.rawg.io/media/games/4be/4be6a6ad0364751a96229c56bf69be59.jpg"
            }
        ],
        "image": "God_of_War.jpg",
        "rating": 4.6,
        "platforms": [
            "PlayStation 5",
            "PC",
            "PlayStation 4"
        ]
    },
    {
        "id": 10213,
        "name": "Dota 2",
        "genres": [
            {
                "id": 4,
                "name": "Action",
                "slug": "action",
                "games_count": 134093,
                "image_background": "https://media.rawg.io/media/games/c4b/c4b0cab189e73432de3a250d8cf1c84e.jpg"
            },
            {
                "id": 59,
                "name": "Massively Multiplayer",
                "slug": "massively-multiplayer",
                "games_count": 2655,
                "image_background": "https://media.rawg.io/media/games/11f/11fd681c312c14644ab360888dba3486.jpg"
            }
        ],
        "image": "Dota_2.jpg",
        "rating": 3.09,
        "platforms": [
            "PC",
            "macOS",
            "Linux"
        ]
    },
    {
        "id": 29028,
        "name": "Metro 2033",
        "genres": [
            {
                "id": 4,
                "name": "Action",
                "slug": "action",
                "games_count": 134093,
                "image_background": "https://media.rawg.io/media/games/c4b/c4b0cab189e73432de3a250d8cf1c84e.jpg"
            },
            {
                "id": 2,
                "name": "Shooter",
                "slug": "shooter",
                "games_count": 45301,
                "image_background": "https://media.rawg.io/media/games/7a2/7a2500ee8b2c0e1ff268bb4479463dea.jpg"
            }
        ],
        "image": "Metro_2033.jpg",
        "rating": 3.91,
        "platforms": [
            "Xbox 360",
            "PC"
        ]
    },
    {
        "id": 3192,
        "name": "Metal Gear Solid V: The Phantom Pain",
        "genres": [
            {
                "id": 4,
                "name": "Action",
                "slug": "action",
                "games_count": 134093,
                "image_background": "https://media.rawg.io/media/games/c4b/c4b0cab189e73432de3a250d8cf1c84e.jpg"
            },
            {
                "id": 2,
                "name": "Shooter",
                "slug": "shooter",
                "games_count": 45301,
                "image_background": "https://media.rawg.io/media/games/7a2/7a2500ee8b2c0e1ff268bb4479463dea.jpg"
            }
        ],
        "image": "Metal_Gear_V.jpg",
        "rating": 4.17,
        "platforms": [
            "Xbox One",
            "PlayStation 3",
            "PlayStation 4",
            "Xbox 360",
            "PC"
        ]
    },
    {
        "id": 766,
        "name": "Warframe",
        "genres": [
            {
                "id": 4,
                "name": "Action",
                "slug": "action",
                "games_count": 134093,
                "image_background": "https://media.rawg.io/media/games/c4b/c4b0cab189e73432de3a250d8cf1c84e.jpg"
            },
            {
                "id": 2,
                "name": "Shooter",
                "slug": "shooter",
                "games_count": 45301,
                "image_background": "https://media.rawg.io/media/games/7a2/7a2500ee8b2c0e1ff268bb4479463dea.jpg"
            },
            {
                "id": 59,
                "name": "Massively Multiplayer",
                "slug": "massively-multiplayer",
                "games_count": 2655,
                "image_background": "https://media.rawg.io/media/games/11f/11fd681c312c14644ab360888dba3486.jpg"
            }
        ],
        "image": "Warframe.jpg",
        "rating": 3.43,
        "platforms": [
            "Xbox Series S/X",
            "PlayStation 5",
            "PlayStation 4",
            "Xbox One",
            "Nintendo Switch",
            "PC"
        ]
    },
    {
        "id": 23027,
        "name": "The Walking Dead: Season 1",
        "genres": [
            {
                "id": 3,
                "name": "Adventure",
                "slug": "adventure",
                "games_count": 99466,
                "image_background": "https://media.rawg.io/media/games/26d/26d4437715bee60138dab4a7c8c59c92.jpg"
            }
        ],
        "image": "The_Walking_Dead_Season_1.jpg",
        "rating": 4.3,
        "platforms": [
            "Android",
            "PS Vita",
            "PlayStation 4",
            "PlayStation 3",
            "Xbox 360",
            "Nintendo Switch",
            "macOS",
            "PC",
            "iOS",
            "Xbox One"
        ]
    },
    {
        "id": 7689,
        "name": "Rise of the Tomb Raider",
        "genres": [
            {
                "id": 4,
                "name": "Action",
                "slug": "action",
                "games_count": 134093,
                "image_background": "https://media.rawg.io/media/games/c4b/c4b0cab189e73432de3a250d8cf1c84e.jpg"
            }
        ],
        "image": "Rise_of_the_Tomb_Raider.jpg",
        "rating": 4.01,
        "platforms": [
            "PlayStation 4",
            "macOS",
            "PC",
            "Xbox One"
        ]
    },
    {
        "id": 422,
        "name": "Terraria",
        "genres": [
            {
                "id": 4,
                "name": "Action",
                "slug": "action",
                "games_count": 134093,
                "image_background": "https://media.rawg.io/media/games/c4b/c4b0cab189e73432de3a250d8cf1c84e.jpg"
            },
            {
                "id": 51,
                "name": "Indie",
                "slug": "indie",
                "games_count": 40791,
                "image_background": "https://media.rawg.io/media/games/dd5/dd50d4266915d56dd5b63ae1bf72606a.jpg"
            },
            {
                "id": 83,
                "name": "Platformer",
                "slug": "platformer",
                "games_count": 73872,
                "image_background": "https://media.rawg.io/media/games/8a0/8a02f84a5916ede2f923b88d5f8217ba.jpg"
            }
        ],
        "image": "Terraria.jpg",
        "rating": 4.02,
        "platforms": [
            "Xbox 360",
            "Wii U",
            "PlayStation 3",
            "Nintendo Switch",
            "macOS",
            "Linux",
            "Nintendo 3DS",
            "PC",
            "Xbox One",
            "PlayStation 4",
            "PS Vita",
            "iOS",
            "Android"
        ]
    },
    {
        "id": 16944,
        "name": "The Witcher 2: Assassins of Kings Enhanced Edition",
        "genres": [
            {
                "id": 5,
                "name": "RPG",
                "slug": "role-playing-games-rpg",
                "games_count": 40860,
                "image_background": "https://media.rawg.io/media/games/d82/d82990b9c67ba0d2d09d4e6fa88885a7.jpg"
            }
        ],
        "image": "The_Witcher_2.jpg",
        "rating": 4.2,
        "platforms": [
            "Xbox 360",
            "PC",
            "macOS"
        ]
    },
    {
        "id": 3287,
        "name": "Batman: Arkham Knight",
        "genres": [
            {
                "id": 4,
                "name": "Action",
                "slug": "action",
                "games_count": 134093,
                "image_background": "https://media.rawg.io/media/games/c4b/c4b0cab189e73432de3a250d8cf1c84e.jpg"
            }
        ],
        "image": "Batman_Arkham_Knight.jpg",
        "rating": 4.22,
        "platforms": [
            "PC",
            "Xbox One",
            "PlayStation 4"
        ]
    },
    {
        "id": 19103,
        "name": "Half-Life 2: Lost Coast",
        "genres": [
            {
                "id": 4,
                "name": "Action",
                "slug": "action",
                "games_count": 134093,
                "image_background": "https://media.rawg.io/media/games/c4b/c4b0cab189e73432de3a250d8cf1c84e.jpg"
            }
        ],
        "image": "Half_Life_2_Lost_Coast.jpg",
        "rating": 3.46,
        "platforms": [
            "macOS",
            "Linux",
            "PC"
        ]
    },
    {
        "id": 11973,
        "name": "Middle-earth: Shadow of Mordor",
        "genres": [
            {
                "id": 4,
                "name": "Action",
                "slug": "action",
                "games_count": 134093,
                "image_background": "https://media.rawg.io/media/games/c4b/c4b0cab189e73432de3a250d8cf1c84e.jpg"
            },
            {
                "id": 5,
                "name": "RPG",
                "slug": "role-playing-games-rpg",
                "games_count": 40860,
                "image_background": "https://media.rawg.io/media/games/d82/d82990b9c67ba0d2d09d4e6fa88885a7.jpg"
            }
        ],
        "image": "Middle_earth_Shadow_of_Mordor.jpg",
        "rating": 3.88,
        "platforms": [
            "Linux",
            "Xbox One",
            "Xbox 360",
            "PlayStation 3",
            "PlayStation 4",
            "macOS",
            "PC"
        ]
    },
    {
        "id": 10035,
        "name": "Hitman",
        "genres": [
            {
                "id": 4,
                "name": "Action",
                "slug": "action",
                "games_count": 134093,
                "image_background": "https://media.rawg.io/media/games/c4b/c4b0cab189e73432de3a250d8cf1c84e.jpg"
            },
            {
                "id": 2,
                "name": "Shooter",
                "slug": "shooter",
                "games_count": 45301,
                "image_background": "https://media.rawg.io/media/games/7a2/7a2500ee8b2c0e1ff268bb4479463dea.jpg"
            },
            {
                "id": 14,
                "name": "Simulation",
                "slug": "simulation",
                "games_count": 51730,
                "image_background": "https://media.rawg.io/media/games/651/651ae84f2d5e36206aad90976a453329.jpg"
            }
        ],
        "image": "Hitman.jpg",
        "rating": 3.93,
        "platforms": [
            "Linux",
            "macOS",
            "PC",
            "PlayStation 4",
            "Xbox One"
        ]
    },
    {
        "id": 416,
        "name": "Grand Theft Auto: San Andreas",
        "genres": [
            {
                "id": 4,
                "name": "Action",
                "slug": "action",
                "games_count": 134093,
                "image_background": "https://media.rawg.io/media/games/c4b/c4b0cab189e73432de3a250d8cf1c84e.jpg"
            },
            {
                "id": 3,
                "name": "Adventure",
                "slug": "adventure",
                "games_count": 99466,
                "image_background": "https://media.rawg.io/media/games/26d/26d4437715bee60138dab4a7c8c59c92.jpg"
            }
        ],
        "image": "Grand_Theft_Auto_San_Andreas.jpg",
        "rating": 4.51,
        "platforms": [
            "Xbox",
            "PlayStation 4",
            "PlayStation 3",
            "PlayStation 2",
            "Xbox 360",
            "macOS",
            "PC",
            "iOS",
            "Xbox One",
            "Android"
        ]
    },
    {
        "id": 4427,
        "name": "BioShock 2",
        "genres": [
            {
                "id": 4,
                "name": "Action",
                "slug": "action",
                "games_count": 134093,
                "image_background": "https://media.rawg.io/media/games/c4b/c4b0cab189e73432de3a250d8cf1c84e.jpg"
            },
            {
                "id": 2,
                "name": "Shooter",
                "slug": "shooter",
                "games_count": 45301,
                "image_background": "https://media.rawg.io/media/games/7a2/7a2500ee8b2c0e1ff268bb4479463dea.jpg"
            }
        ],
        "image": "BioShock_2.jpg",
        "rating": 4.07,
        "platforms": [
            "PlayStation 4",
            "Xbox One",
            "Nintendo Switch",
            "PC",
            "macOS",
            "Xbox 360",
            "PlayStation 3"
        ]
    },
    {
        "id": 17822,
        "name": "The Witcher: Enhanced Edition Director's Cut",
        "genres": [
            {
                "id": 4,
                "name": "Action",
                "slug": "action",
                "games_count": 134093,
                "image_background": "https://media.rawg.io/media/games/c4b/c4b0cab189e73432de3a250d8cf1c84e.jpg"
            },
            {
                "id": 5,
                "name": "RPG",
                "slug": "role-playing-games-rpg",
                "games_count": 40860,
                "image_background": "https://media.rawg.io/media/games/d82/d82990b9c67ba0d2d09d4e6fa88885a7.jpg"
            }
        ],
        "image": "The_Witcher_Enhanced_Edition_Director_Cut.jpg",
        "rating": 4.06,
        "platforms": [
            "macOS",
            "PC"
        ]
    },
    {
        "id": 19710,
        "name": "Half-Life 2: Episode One",
        "genres": [
            {
                "id": 4,
                "name": "Action",
                "slug": "action",
                "games_count": 134093,
                "image_background": "https://media.rawg.io/media/games/c4b/c4b0cab189e73432de3a250d8cf1c84e.jpg"
            },
            {
                "id": 2,
                "name": "Shooter",
                "slug": "shooter",
                "games_count": 45301,
                "image_background": "https://media.rawg.io/media/games/7a2/7a2500ee8b2c0e1ff268bb4479463dea.jpg"
            }
        ],
        "image": "Half_Life_2_Episode_One.jpg",
        "rating": 4.39,
        "platforms": [
            "Linux",
            "PC",
            "Xbox 360",
            "Android",
            "macOS"
        ]
    },
    {
        "id": 4252,
        "name": "Mirror's Edge",
        "genres": [
            {
                "id": 4,
                "name": "Action",
                "slug": "action",
                "games_count": 134093,
                "image_background": "https://media.rawg.io/media/games/c4b/c4b0cab189e73432de3a250d8cf1c84e.jpg"
            }
        ],
        "image": "Mirror_Edge.jpg",
        "rating": 4.07,
        "platforms": [
            "PlayStation 3",
            "Xbox 360",
            "PC"
        ]
    },
    {
        "id": 2462,
        "name": "Uncharted 4: A Thief’s End",
        "genres": [
            {
                "id": 4,
                "name": "Action",
                "slug": "action",
                "games_count": 134093,
                "image_background": "https://media.rawg.io/media/games/c4b/c4b0cab189e73432de3a250d8cf1c84e.jpg"
            },
            {
                "id": 3,
                "name": "Adventure",
                "slug": "adventure",
                "games_count": 99466,
                "image_background": "https://media.rawg.io/media/games/26d/26d4437715bee60138dab4a7c8c59c92.jpg"
            }
        ],
        "image": "Uncharted_4.jpg",
        "rating": 4.52,
        "platforms": [
            "PlayStation 4",
            "PlayStation 5",
            "PC"
        ]
    },
    {
        "id": 19709,
        "name": "Half-Life 2: Episode Two",
        "genres": [
            {
                "id": 4,
                "name": "Action",
                "slug": "action",
                "games_count": 134093,
                "image_background": "https://media.rawg.io/media/games/c4b/c4b0cab189e73432de3a250d8cf1c84e.jpg"
            },
            {
                "id": 2,
                "name": "Shooter",
                "slug": "shooter",
                "games_count": 45301,
                "image_background": "https://media.rawg.io/media/games/7a2/7a2500ee8b2c0e1ff268bb4479463dea.jpg"
            },
            {
                "id": 7,
                "name": "Puzzle",
                "slug": "puzzle",
                "games_count": 75573,
                "image_background": "https://media.rawg.io/media/games/2e1/2e187b31e5cee21c110bd16798d75fab.jpg"
            }
        ],
        "image": "Half_Life_2_Episode_Two.jpg",
        "rating": 4.45,
        "platforms": [
            "PC",
            "Linux",
            "macOS",
            "Xbox 360",
            "Android"
        ]
    },
    {
        "id": 3612,
        "name": "Hotline Miami",
        "genres": [
            {
                "id": 4,
                "name": "Action",
                "slug": "action",
                "games_count": 134093,
                "image_background": "https://media.rawg.io/media/games/c4b/c4b0cab189e73432de3a250d8cf1c84e.jpg"
            },
            {
                "id": 2,
                "name": "Shooter",
                "slug": "shooter",
                "games_count": 45301,
                "image_background": "https://media.rawg.io/media/games/7a2/7a2500ee8b2c0e1ff268bb4479463dea.jpg"
            },
            {
                "id": 11,
                "name": "Arcade",
                "slug": "arcade",
                "games_count": 22371,
                "image_background": "https://media.rawg.io/media/games/cfe/cfe114c081281960bd79ace5209c0a4a.jpg"
            },
            {
                "id": 51,
                "name": "Indie",
                "slug": "indie",
                "games_count": 40791,
                "image_background": "https://media.rawg.io/media/games/dd5/dd50d4266915d56dd5b63ae1bf72606a.jpg"
            }
        ],
        "image": "Hotline_Miami.jpg",
        "rating": 4.36,
        "platforms": [
            "Linux",
            "Nintendo Switch",
            "Xbox One",
            "PlayStation 4",
            "PS Vita",
            "PC"
        ]
    },
    {
        "id": 1447,
        "name": "Deus Ex: Mankind Divided",
        "genres": [
            {
                "id": 4,
                "name": "Action",
                "slug": "action",
                "games_count": 134093,
                "image_background": "https://media.rawg.io/media/games/c4b/c4b0cab189e73432de3a250d8cf1c84e.jpg"
            },
            {
                "id": 5,
                "name": "RPG",
                "slug": "role-playing-games-rpg",
                "games_count": 40860,
                "image_background": "https://media.rawg.io/media/games/d82/d82990b9c67ba0d2d09d4e6fa88885a7.jpg"
            }
        ],
        "image": "Deus_Ex_Mankind_Divided.jpg",
        "rating": 3.96,
        "platforms": [
            "Xbox One",
            "Linux",
            "macOS",
            "PlayStation 4",
            "PC"
        ]
    },
    {
        "id": 4332,
        "name": "Spec Ops: The Line",
        "genres": [
            {
                "id": 4,
                "name": "Action",
                "slug": "action",
                "games_count": 134093,
                "image_background": "https://media.rawg.io/media/games/c4b/c4b0cab189e73432de3a250d8cf1c84e.jpg"
            },
            {
                "id": 2,
                "name": "Shooter",
                "slug": "shooter",
                "games_count": 45301,
                "image_background": "https://media.rawg.io/media/games/7a2/7a2500ee8b2c0e1ff268bb4479463dea.jpg"
            }
        ],
        "image": "Spec_Ops_The_Line.jpg",
        "rating": 4.06,
        "platforms": [
            "Xbox 360",
            "PlayStation 3",
            "Xbox One",
            "PC"
        ]
    },
    {
        "id": 41494,
        "name": "Cyberpunk 2077",
        "genres": [
            {
                "id": 4,
                "name": "Action",
                "slug": "action",
                "games_count": 134093,
                "image_background": "https://media.rawg.io/media/games/c4b/c4b0cab189e73432de3a250d8cf1c84e.jpg"
            },
            {
                "id": 3,
                "name": "Adventure",
                "slug": "adventure",
                "games_count": 99466,
                "image_background": "https://media.rawg.io/media/games/26d/26d4437715bee60138dab4a7c8c59c92.jpg"
            },
            {
                "id": 5,
                "name": "RPG",
                "slug": "role-playing-games-rpg",
                "games_count": 40860,
                "image_background": "https://media.rawg.io/media/games/d82/d82990b9c67ba0d2d09d4e6fa88885a7.jpg"
            }
        ],
        "image": "Cyberpunk_2077.jpg",
        "rating": 4.02,
        "platforms": [
            "PC",
            "Xbox Series S/X",
            "PlayStation 5",
            "Xbox One",
            "PlayStation 4"
        ]
    },
    {
        "id": 3790,
        "name": "Outlast",
        "genres": [
            {
                "id": 4,
                "name": "Action",
                "slug": "action",
                "games_count": 134093,
                "image_background": "https://media.rawg.io/media/games/c4b/c4b0cab189e73432de3a250d8cf1c84e.jpg"
            },
            {
                "id": 3,
                "name": "Adventure",
                "slug": "adventure",
                "games_count": 99466,
                "image_background": "https://media.rawg.io/media/games/26d/26d4437715bee60138dab4a7c8c59c92.jpg"
            },
            {
                "id": 51,
                "name": "Indie",
                "slug": "indie",
                "games_count": 40791,
                "image_background": "https://media.rawg.io/media/games/dd5/dd50d4266915d56dd5b63ae1bf72606a.jpg"
            }
        ],
        "image": "Outlast.jpg",
        "rating": 3.68,
        "platforms": [
            "Xbox One",
            "PlayStation 4",
            "Nintendo Switch",
            "macOS",
            "PC",
            "Linux"
        ]
    },
    {
        "id": 19487,
        "name": "Alan Wake",
        "genres": [
            {
                "id": 4,
                "name": "Action",
                "slug": "action",
                "games_count": 134093,
                "image_background": "https://media.rawg.io/media/games/c4b/c4b0cab189e73432de3a250d8cf1c84e.jpg"
            },
            {
                "id": 2,
                "name": "Shooter",
                "slug": "shooter",
                "games_count": 45301,
                "image_background": "https://media.rawg.io/media/games/7a2/7a2500ee8b2c0e1ff268bb4479463dea.jpg"
            },
            {
                "id": 3,
                "name": "Adventure",
                "slug": "adventure",
                "games_count": 99466,
                "image_background": "https://media.rawg.io/media/games/26d/26d4437715bee60138dab4a7c8c59c92.jpg"
            }
        ],
        "image": "Alan_Wake.jpg",
        "rating": 4.12,
        "platforms": [
            "Xbox 360",
            "Xbox One",
            "PC"
        ]
    },
    {
        "id": 10754,
        "name": "BioShock Remastered",
        "genres": [
            {
                "id": 2,
                "name": "Shooter",
                "slug": "shooter",
                "games_count": 45301,
                "image_background": "https://media.rawg.io/media/games/7a2/7a2500ee8b2c0e1ff268bb4479463dea.jpg"
            }
        ],
        "image": "BioShock_Remastered.jpg",
        "rating": 4.26,
        "platforms": [
            "Nintendo Switch",
            "Xbox One",
            "macOS",
            "PlayStation 4",
            "PC"
        ]
    },
    {
        "id": 13668,
        "name": "Amnesia: The Dark Descent",
        "genres": [
            {
                "id": 4,
                "name": "Action",
                "slug": "action",
                "games_count": 134093,
                "image_background": "https://media.rawg.io/media/games/c4b/c4b0cab189e73432de3a250d8cf1c84e.jpg"
            },
            {
                "id": 3,
                "name": "Adventure",
                "slug": "adventure",
                "games_count": 99466,
                "image_background": "https://media.rawg.io/media/games/26d/26d4437715bee60138dab4a7c8c59c92.jpg"
            },
            {
                "id": 51,
                "name": "Indie",
                "slug": "indie",
                "games_count": 40791,
                "image_background": "https://media.rawg.io/media/games/dd5/dd50d4266915d56dd5b63ae1bf72606a.jpg"
            }
        ],
        "image": "Amnesia_The_Dark_Descent.jpg",
        "rating": 3.64,
        "platforms": [
            "Linux",
            "macOS",
            "PC"
        ]
    },
    {
        "id": 4386,
        "name": "Saints Row: The Third",
        "genres": [
            {
                "id": 4,
                "name": "Action",
                "slug": "action",
                "games_count": 134093,
                "image_background": "https://media.rawg.io/media/games/c4b/c4b0cab189e73432de3a250d8cf1c84e.jpg"
            },
            {
                "id": 3,
                "name": "Adventure",
                "slug": "adventure",
                "games_count": 99466,
                "image_background": "https://media.rawg.io/media/games/26d/26d4437715bee60138dab4a7c8c59c92.jpg"
            }
        ],
        "image": "Saints_Row_The_Third.jpg",
        "rating": 3.93,
        "platforms": [
            "PC",
            "Xbox One",
            "Xbox 360",
            "PlayStation 3",
            "Linux"
        ]
    },
    {
        "id": 58134,
        "name": "Marvel's Spider-Man",
        "genres": [
            {
                "id": 4,
                "name": "Action",
                "slug": "action",
                "games_count": 134351,
                "image_background": "https://media.rawg.io/media/games/f87/f87457e8347484033cb34cde6101d08d.jpg"
            },
            {
                "id": 3,
                "name": "Adventure",
                "slug": "adventure",
                "games_count": 99679,
                "image_background": "https://media.rawg.io/media/games/4be/4be6a6ad0364751a96229c56bf69be59.jpg"
            }
        ],
        "image": "Marvel_Spider_Man.jpg",
        "rating": 4.46,
        "platforms": [
            "PlayStation 4",
            "PlayStation 5"
        ]
    },
    {
        "id": 2551,
        "name": "Dark Souls III",
        "genres": [
            {
                "id": 4,
                "name": "Action",
                "slug": "action",
                "games_count": 134093,
                "image_background": "https://media.rawg.io/media/games/c4b/c4b0cab189e73432de3a250d8cf1c84e.jpg"
            },
            {
                "id": 5,
                "name": "RPG",
                "slug": "role-playing-games-rpg",
                "games_count": 40860,
                "image_background": "https://media.rawg.io/media/games/d82/d82990b9c67ba0d2d09d4e6fa88885a7.jpg"
            }
        ],
        "image": "Dark_Souls_III.jpg",
        "rating": 4.4,
        "platforms": [
            "PlayStation 4",
            "Xbox One",
            "PC"
        ]
    },
    {
        "id": 4161,
        "name": "Far Cry 3",
        "genres": [
            {
                "id": 4,
                "name": "Action",
                "slug": "action",
                "games_count": 134093,
                "image_background": "https://media.rawg.io/media/games/c4b/c4b0cab189e73432de3a250d8cf1c84e.jpg"
            },
            {
                "id": 2,
                "name": "Shooter",
                "slug": "shooter",
                "games_count": 45301,
                "image_background": "https://media.rawg.io/media/games/7a2/7a2500ee8b2c0e1ff268bb4479463dea.jpg"
            }
        ],
        "image": "Far_Cry_3.jpg",
        "rating": 4.24,
        "platforms": [
            "PlayStation 4",
            "Xbox One",
            "Xbox 360",
            "PlayStation 3",
            "PC"
        ]
    },
    {
        "id": 11936,
        "name": "Half-Life 2: Deathmatch",
        "genres": [
            {
                "id": 4,
                "name": "Action",
                "slug": "action",
                "games_count": 134093,
                "image_background": "https://media.rawg.io/media/games/c4b/c4b0cab189e73432de3a250d8cf1c84e.jpg"
            }
        ],
        "image": "Half_Life_2_Deathmatch.jpg",
        "rating": 3.3,
        "platforms": [
            "Linux",
            "macOS",
            "PC"
        ]
    },
    {
        "id": 4828,
        "name": "Borderlands",
        "genres": [
            {
                "id": 4,
                "name": "Action",
                "slug": "action",
                "games_count": 134093,
                "image_background": "https://media.rawg.io/media/games/c4b/c4b0cab189e73432de3a250d8cf1c84e.jpg"
            },
            {
                "id": 2,
                "name": "Shooter",
                "slug": "shooter",
                "games_count": 45301,
                "image_background": "https://media.rawg.io/media/games/7a2/7a2500ee8b2c0e1ff268bb4479463dea.jpg"
            },
            {
                "id": 5,
                "name": "RPG",
                "slug": "role-playing-games-rpg",
                "games_count": 40860,
                "image_background": "https://media.rawg.io/media/games/d82/d82990b9c67ba0d2d09d4e6fa88885a7.jpg"
            }
        ],
        "image": "Borderlands.jpg",
        "rating": 3.84,
        "platforms": [
            "Xbox 360",
            "PlayStation 3",
            "Xbox One",
            "Nintendo Switch",
            "PC"
        ]
    },
    {
        "id": 3144,
        "name": "Super Meat Boy",
        "genres": [
            {
                "id": 51,
                "name": "Indie",
                "slug": "indie",
                "games_count": 40791,
                "image_background": "https://media.rawg.io/media/games/dd5/dd50d4266915d56dd5b63ae1bf72606a.jpg"
            },
            {
                "id": 83,
                "name": "Platformer",
                "slug": "platformer",
                "games_count": 73872,
                "image_background": "https://media.rawg.io/media/games/8a0/8a02f84a5916ede2f923b88d5f8217ba.jpg"
            }
        ],
        "image": "Super_Meat_Boy.jpg",
        "rating": 3.97,
        "platforms": [
            "Web",
            "Android",
            "PS Vita",
            "PlayStation 4",
            "Xbox 360",
            "Wii U",
            "Nintendo Switch",
            "Linux",
            "macOS",
            "PC"
        ]
    },
    {
        "id": 4514,
        "name": "L.A. Noire",
        "genres": [
            {
                "id": 4,
                "name": "Action",
                "slug": "action",
                "games_count": 134093,
                "image_background": "https://media.rawg.io/media/games/c4b/c4b0cab189e73432de3a250d8cf1c84e.jpg"
            },
            {
                "id": 3,
                "name": "Adventure",
                "slug": "adventure",
                "games_count": 99466,
                "image_background": "https://media.rawg.io/media/games/26d/26d4437715bee60138dab4a7c8c59c92.jpg"
            },
            {
                "id": 7,
                "name": "Puzzle",
                "slug": "puzzle",
                "games_count": 75573,
                "image_background": "https://media.rawg.io/media/games/2e1/2e187b31e5cee21c110bd16798d75fab.jpg"
            }
        ],
        "image": "L_A_Noire.jpg",
        "rating": 4.16,
        "platforms": [
            "PlayStation 4",
            "PlayStation 3",
            "Xbox 360",
            "PC",
            "Xbox One",
            "Nintendo Switch"
        ]
    },
    {
        "id": 3696,
        "name": "Wolfenstein: The New Order",
        "genres": [
            {
                "id": 4,
                "name": "Action",
                "slug": "action",
                "games_count": 134093,
                "image_background": "https://media.rawg.io/media/games/c4b/c4b0cab189e73432de3a250d8cf1c84e.jpg"
            },
            {
                "id": 2,
                "name": "Shooter",
                "slug": "shooter",
                "games_count": 45301,
                "image_background": "https://media.rawg.io/media/games/7a2/7a2500ee8b2c0e1ff268bb4479463dea.jpg"
            }
        ],
        "image": "Wolfenstein_The_New_Order.jpg",
        "rating": 4.19,
        "platforms": [
            "PlayStation 4",
            "PlayStation 3",
            "Xbox 360",
            "PC",
            "Xbox One"
        ]
    },
    {
        "id": 9767,
        "name": "Hollow Knight",
        "genres": [
            {
                "id": 4,
                "name": "Action",
                "slug": "action",
                "games_count": 134093,
                "image_background": "https://media.rawg.io/media/games/c4b/c4b0cab189e73432de3a250d8cf1c84e.jpg"
            },
            {
                "id": 51,
                "name": "Indie",
                "slug": "indie",
                "games_count": 40791,
                "image_background": "https://media.rawg.io/media/games/dd5/dd50d4266915d56dd5b63ae1bf72606a.jpg"
            },
            {
                "id": 83,
                "name": "Platformer",
                "slug": "platformer",
                "games_count": 73872,
                "image_background": "https://media.rawg.io/media/games/8a0/8a02f84a5916ede2f923b88d5f8217ba.jpg"
            }
        ],
        "image": "Hollow_Knight.jpg",
        "rating": 4.4,
        "platforms": [
            "Nintendo Switch",
            "macOS",
            "Linux",
            "Xbox One",
            "PlayStation 4",
            "PC"
        ]
    },
    {
        "id": 3636,
        "name": "The Last Of Us Remastered",
        "genres": [
            {
                "id": 4,
                "name": "Action",
                "slug": "action",
                "games_count": 134093,
                "image_background": "https://media.rawg.io/media/games/c4b/c4b0cab189e73432de3a250d8cf1c84e.jpg"
            },
            {
                "id": 3,
                "name": "Adventure",
                "slug": "adventure",
                "games_count": 99466,
                "image_background": "https://media.rawg.io/media/games/26d/26d4437715bee60138dab4a7c8c59c92.jpg"
            }
        ],
        "image": "The_Last_Of_Us_Remastered.jpg",
        "rating": 4.69,
        "platforms": [
            "PlayStation 4"
        ]
    },
    {
        "id": 13633,
        "name": "Sid Meier's Civilization V",
        "genres": [
            {
                "id": 10,
                "name": "Strategy",
                "slug": "strategy",
                "games_count": 41420,
                "image_background": "https://media.rawg.io/media/games/651/651ae84f2d5e36206aad90976a453329.jpg"
            }
        ],
        "image": "Sid_Meier_Civilization_V.jpg",
        "rating": 4.29,
        "platforms": [
            "Linux",
            "macOS",
            "PC"
        ]
    },
    {
        "id": 41,
        "name": "Little Nightmares",
        "genres": [
            {
                "id": 4,
                "name": "Action",
                "slug": "action",
                "games_count": 134093,
                "image_background": "https://media.rawg.io/media/games/c4b/c4b0cab189e73432de3a250d8cf1c84e.jpg"
            },
            {
                "id": 83,
                "name": "Platformer",
                "slug": "platformer",
                "games_count": 73872,
                "image_background": "https://media.rawg.io/media/games/8a0/8a02f84a5916ede2f923b88d5f8217ba.jpg"
            }
        ],
        "image": "Little_Nightmares.jpg",
        "rating": 4.09,
        "platforms": [
            "Xbox One",
            "PlayStation 4",
            "Nintendo Switch",
            "PC"
        ]
    },
    {
        "id": 4806,
        "name": "Mass Effect 2",
        "genres": [
            {
                "id": 4,
                "name": "Action",
                "slug": "action",
                "games_count": 134093,
                "image_background": "https://media.rawg.io/media/games/c4b/c4b0cab189e73432de3a250d8cf1c84e.jpg"
            },
            {
                "id": 5,
                "name": "RPG",
                "slug": "role-playing-games-rpg",
                "games_count": 40860,
                "image_background": "https://media.rawg.io/media/games/d82/d82990b9c67ba0d2d09d4e6fa88885a7.jpg"
            }
        ],
        "image": "Mass_Effect_2.jpg",
        "rating": 4.48,
        "platforms": [
            "PC",
            "Xbox One",
            "PlayStation 3",
            "Xbox 360"
        ]
    },
    {
        "id": 4570,
        "name": "Dead Space",
        "genres": [
            {
                "id": 4,
                "name": "Action",
                "slug": "action",
                "games_count": 134093,
                "image_background": "https://media.rawg.io/media/games/c4b/c4b0cab189e73432de3a250d8cf1c84e.jpg"
            },
            {
                "id": 2,
                "name": "Shooter",
                "slug": "shooter",
                "games_count": 45301,
                "image_background": "https://media.rawg.io/media/games/7a2/7a2500ee8b2c0e1ff268bb4479463dea.jpg"
            }
        ],
        "image": "Dead_Space.jpg",
        "rating": 4.38,
        "platforms": [
            "PC",
            "PlayStation 3",
            "Xbox One",
            "Xbox 360"
        ]
    },
    {
        "id": 18080,
        "name": "Half-Life",
        "genres": [
            {
                "id": 4,
                "name": "Action",
                "slug": "action",
                "games_count": 134093,
                "image_background": "https://media.rawg.io/media/games/c4b/c4b0cab189e73432de3a250d8cf1c84e.jpg"
            },
            {
                "id": 2,
                "name": "Shooter",
                "slug": "shooter",
                "games_count": 45301,
                "image_background": "https://media.rawg.io/media/games/7a2/7a2500ee8b2c0e1ff268bb4479463dea.jpg"
            },
            {
                "id": 7,
                "name": "Puzzle",
                "slug": "puzzle",
                "games_count": 75573,
                "image_background": "https://media.rawg.io/media/games/2e1/2e187b31e5cee21c110bd16798d75fab.jpg"
            },
            {
                "id": 83,
                "name": "Platformer",
                "slug": "platformer",
                "games_count": 73872,
                "image_background": "https://media.rawg.io/media/games/8a0/8a02f84a5916ede2f923b88d5f8217ba.jpg"
            }
        ],
        "image": "Half_Life_Logo.jpg",
        "rating": 4.4,
        "platforms": [
            "PlayStation 2",
            "Linux",
            "macOS",
            "PC"
        ]
    },
    {
        "id": 17540,
        "name": "Injustice: Gods Among Us Ultimate Edition",
        "genres": [
            {
                "id": 4,
                "name": "Action",
                "slug": "action",
                "games_count": 134093,
                "image_background": "https://media.rawg.io/media/games/c4b/c4b0cab189e73432de3a250d8cf1c84e.jpg"
            },
            {
                "id": 11,
                "name": "Arcade",
                "slug": "arcade",
                "games_count": 22371,
                "image_background": "https://media.rawg.io/media/games/cfe/cfe114c081281960bd79ace5209c0a4a.jpg"
            },
            {
                "id": 6,
                "name": "Fighting",
                "slug": "fighting",
                "games_count": 8662,
                "image_background": "https://media.rawg.io/media/games/9f3/9f3c513b301d8d7250a64dd7e73c62df.jpg"
            }
        ],
        "image": "Injustice_Gods_Among.jpg",
        "rating": 3.56,
        "platforms": [
            "PlayStation 4",
            "PS Vita",
            "PC",
            "Xbox 360",
            "PlayStation 3"
        ]
    },
    {
        "id": 290856,
        "name": "Apex Legends",
        "genres": [
            {
                "id": 4,
                "name": "Action",
                "slug": "action",
                "games_count": 134351,
                "image_background": "https://media.rawg.io/media/games/f87/f87457e8347484033cb34cde6101d08d.jpg"
            },
            {
                "id": 2,
                "name": "Shooter",
                "slug": "shooter",
                "games_count": 45427,
                "image_background": "https://media.rawg.io/media/games/5c0/5c0dd63002cb23f804aab327d40ef119.jpg"
            },
            {
                "id": 3,
                "name": "Adventure",
                "slug": "adventure",
                "games_count": 99679,
                "image_background": "https://media.rawg.io/media/games/4be/4be6a6ad0364751a96229c56bf69be59.jpg"
            },
            {
                "id": 59,
                "name": "Massively Multiplayer",
                "slug": "massively-multiplayer",
                "games_count": 2656,
                "image_background": "https://media.rawg.io/media/games/34b/34b1f1850a1c06fd971bc6ab3ac0ce0e.jpg"
            }
        ],
        "image": "Apex_Legends.jpg",
        "rating": 3.67,
        "platforms": [
            "macOS",
            "Nintendo Switch",
            "Xbox One",
            "PlayStation 4",
            "PC"
        ]
    },
    {
        "id": 5583,
        "name": "Hitman: Absolution",
        "genres": [
            {
                "id": 4,
                "name": "Action",
                "slug": "action",
                "games_count": 134093,
                "image_background": "https://media.rawg.io/media/games/c4b/c4b0cab189e73432de3a250d8cf1c84e.jpg"
            },
            {
                "id": 2,
                "name": "Shooter",
                "slug": "shooter",
                "games_count": 45301,
                "image_background": "https://media.rawg.io/media/games/7a2/7a2500ee8b2c0e1ff268bb4479463dea.jpg"
            }
        ],
        "image": "Hitman_Absolution.jpg",
        "rating": 3.71,
        "platforms": [
            "PlayStation 3",
            "Xbox 360",
            "macOS",
            "PC",
            "PlayStation 4"
        ]
    },
    {
        "id": 10533,
        "name": "Path of Exile",
        "genres": [
            {
                "id": 4,
                "name": "Action",
                "slug": "action",
                "games_count": 134093,
                "image_background": "https://media.rawg.io/media/games/c4b/c4b0cab189e73432de3a250d8cf1c84e.jpg"
            },
            {
                "id": 5,
                "name": "RPG",
                "slug": "role-playing-games-rpg",
                "games_count": 40860,
                "image_background": "https://media.rawg.io/media/games/d82/d82990b9c67ba0d2d09d4e6fa88885a7.jpg"
            },
            {
                "id": 59,
                "name": "Massively Multiplayer",
                "slug": "massively-multiplayer",
                "games_count": 2655,
                "image_background": "https://media.rawg.io/media/games/11f/11fd681c312c14644ab360888dba3486.jpg"
            },
            {
                "id": 51,
                "name": "Indie",
                "slug": "indie",
                "games_count": 40791,
                "image_background": "https://media.rawg.io/media/games/dd5/dd50d4266915d56dd5b63ae1bf72606a.jpg"
            }
        ],
        "image": "Path_of_Exile.jpg",
        "rating": 3.66,
        "platforms": [
            "Xbox One",
            "PlayStation 4",
            "PC"
        ]
    },
    {
        "id": 362,
        "name": "For Honor",
        "genres": [
            {
                "id": 4,
                "name": "Action",
                "slug": "action",
                "games_count": 134093,
                "image_background": "https://media.rawg.io/media/games/c4b/c4b0cab189e73432de3a250d8cf1c84e.jpg"
            },
            {
                "id": 59,
                "name": "Massively Multiplayer",
                "slug": "massively-multiplayer",
                "games_count": 2655,
                "image_background": "https://media.rawg.io/media/games/11f/11fd681c312c14644ab360888dba3486.jpg"
            }
        ],
        "image": "For_Honor.jpg",
        "rating": 3.3,
        "platforms": [
            "PC",
            "Xbox One",
            "PlayStation 4"
        ]
    },
    {
        "id": 10243,
        "name": "Company of Heroes 2",
        "genres": [
            {
                "id": 10,
                "name": "Strategy",
                "slug": "strategy",
                "games_count": 41420,
                "image_background": "https://media.rawg.io/media/games/651/651ae84f2d5e36206aad90976a453329.jpg"
            },
            {
                "id": 14,
                "name": "Simulation",
                "slug": "simulation",
                "games_count": 51730,
                "image_background": "https://media.rawg.io/media/games/651/651ae84f2d5e36206aad90976a453329.jpg"
            }
        ],
        "image": "Company_of_Heroes_2.jpg",
        "rating": 3.1,
        "platforms": [
            "PC",
            "macOS",
            "Linux"
        ]
    },
    {
        "id": 39,
        "name": "Prey",
        "genres": [
            {
                "id": 4,
                "name": "Action",
                "slug": "action",
                "games_count": 134093,
                "image_background": "https://media.rawg.io/media/games/c4b/c4b0cab189e73432de3a250d8cf1c84e.jpg"
            },
            {
                "id": 2,
                "name": "Shooter",
                "slug": "shooter",
                "games_count": 45301,
                "image_background": "https://media.rawg.io/media/games/7a2/7a2500ee8b2c0e1ff268bb4479463dea.jpg"
            },
            {
                "id": 5,
                "name": "RPG",
                "slug": "role-playing-games-rpg",
                "games_count": 40860,
                "image_background": "https://media.rawg.io/media/games/d82/d82990b9c67ba0d2d09d4e6fa88885a7.jpg"
            }
        ],
        "image": "Prey.jpg",
        "rating": 4.28,
        "platforms": [
            "PlayStation 4",
            "PC",
            "Xbox One"
        ]
    },
    {
        "id": 29177,
        "name": "Detroit: Become Human",
        "genres": [
            {
                "id": 4,
                "name": "Action",
                "slug": "action",
                "games_count": 134093,
                "image_background": "https://media.rawg.io/media/games/c4b/c4b0cab189e73432de3a250d8cf1c84e.jpg"
            },
            {
                "id": 3,
                "name": "Adventure",
                "slug": "adventure",
                "games_count": 99466,
                "image_background": "https://media.rawg.io/media/games/26d/26d4437715bee60138dab4a7c8c59c92.jpg"
            }
        ],
        "image": "Detroit_Become_Human.jpg",
        "rating": 4.28,
        "platforms": [
            "PC",
            "PlayStation 4"
        ]
    },
    {
        "id": 3841,
        "name": "Assassin’s Creed IV: Black Flag",
        "genres": [
            {
                "id": 4,
                "name": "Action",
                "slug": "action",
                "games_count": 134093,
                "image_background": "https://media.rawg.io/media/games/c4b/c4b0cab189e73432de3a250d8cf1c84e.jpg"
            }
        ],
        "image": "Creed_IV_Black_Flag.jpg",
        "rating": 4.1,
        "platforms": [
            "PlayStation 4",
            "PlayStation 3",
            "Wii U",
            "Nintendo Switch",
            "PC",
            "Xbox One",
            "Xbox 360"
        ]
    },
    {
        "id": 9721,
        "name": "Garry's Mod",
        "genres": [
            {
                "id": 4,
                "name": "Action",
                "slug": "action",
                "games_count": 134093,
                "image_background": "https://media.rawg.io/media/games/c4b/c4b0cab189e73432de3a250d8cf1c84e.jpg"
            },
            {
                "id": 3,
                "name": "Adventure",
                "slug": "adventure",
                "games_count": 99466,
                "image_background": "https://media.rawg.io/media/games/26d/26d4437715bee60138dab4a7c8c59c92.jpg"
            },
            {
                "id": 14,
                "name": "Simulation",
                "slug": "simulation",
                "games_count": 51730,
                "image_background": "https://media.rawg.io/media/games/651/651ae84f2d5e36206aad90976a453329.jpg"
            },
            {
                "id": 40,
                "name": "Casual",
                "slug": "casual",
                "games_count": 34964,
                "image_background": "https://media.rawg.io/media/screenshots/054/054bf49d9e736edfda5aa8e9015faf9b.jpeg"
            },
            {
                "id": 51,
                "name": "Indie",
                "slug": "indie",
                "games_count": 40791,
                "image_background": "https://media.rawg.io/media/games/dd5/dd50d4266915d56dd5b63ae1bf72606a.jpg"
            }
        ],
        "image": "Garry_Mod.jpg",
        "rating": 3.77,
        "platforms": [
            "Linux",
            "PC",
            "macOS"
        ]
    },
    {
        "id": 3387,
        "name": "Bloodborne",
        "genres": [
            {
                "id": 4,
                "name": "Action",
                "slug": "action",
                "games_count": 134093,
                "image_background": "https://media.rawg.io/media/games/c4b/c4b0cab189e73432de3a250d8cf1c84e.jpg"
            },
            {
                "id": 5,
                "name": "RPG",
                "slug": "role-playing-games-rpg",
                "games_count": 40860,
                "image_background": "https://media.rawg.io/media/games/d82/d82990b9c67ba0d2d09d4e6fa88885a7.jpg"
            }
        ],
        "image": "Bloodborne.jpg",
        "rating": 4.4,
        "platforms": [
            "PlayStation 4"
        ]
    },
    {
        "id": 430,
        "name": "Grand Theft Auto: Vice City",
        "genres": [
            {
                "id": 4,
                "name": "Action",
                "slug": "action",
                "games_count": 134093,
                "image_background": "https://media.rawg.io/media/games/c4b/c4b0cab189e73432de3a250d8cf1c84e.jpg"
            },
            {
                "id": 3,
                "name": "Adventure",
                "slug": "adventure",
                "games_count": 99466,
                "image_background": "https://media.rawg.io/media/games/26d/26d4437715bee60138dab4a7c8c59c92.jpg"
            }
        ],
        "image": "Grand_Theft_Auto_Vice_City.jpg",
        "rating": 4.45,
        "platforms": [
            "PlayStation 2",
            "PlayStation 3",
            "PlayStation 4",
            "Xbox",
            "Android",
            "iOS",
            "PC",
            "macOS"
        ]
    },
    {
        "id": 4248,
        "name": "Dishonored",
        "genres": [
            {
                "id": 4,
                "name": "Action",
                "slug": "action",
                "games_count": 134093,
                "image_background": "https://media.rawg.io/media/games/c4b/c4b0cab189e73432de3a250d8cf1c84e.jpg"
            },
            {
                "id": 2,
                "name": "Shooter",
                "slug": "shooter",
                "games_count": 45301,
                "image_background": "https://media.rawg.io/media/games/7a2/7a2500ee8b2c0e1ff268bb4479463dea.jpg"
            },
            {
                "id": 3,
                "name": "Adventure",
                "slug": "adventure",
                "games_count": 99466,
                "image_background": "https://media.rawg.io/media/games/26d/26d4437715bee60138dab4a7c8c59c92.jpg"
            },
            {
                "id": 5,
                "name": "RPG",
                "slug": "role-playing-games-rpg",
                "games_count": 40860,
                "image_background": "https://media.rawg.io/media/games/d82/d82990b9c67ba0d2d09d4e6fa88885a7.jpg"
            }
        ],
        "image": "Dishonored.jpg",
        "rating": 4.37,
        "platforms": [
            "PlayStation 4",
            "PlayStation 3",
            "Xbox 360",
            "PC",
            "Xbox One"
        ]
    },
    {
        "id": 4166,
        "name": "Mass Effect",
        "genres": [
            {
                "id": 4,
                "name": "Action",
                "slug": "action",
                "games_count": 134093,
                "image_background": "https://media.rawg.io/media/games/c4b/c4b0cab189e73432de3a250d8cf1c84e.jpg"
            },
            {
                "id": 5,
                "name": "RPG",
                "slug": "role-playing-games-rpg",
                "games_count": 40860,
                "image_background": "https://media.rawg.io/media/games/d82/d82990b9c67ba0d2d09d4e6fa88885a7.jpg"
            }
        ],
        "image": "Mass_Effect.jpg",
        "rating": 4.4,
        "platforms": [
            "Xbox One",
            "Xbox 360",
            "PlayStation 3",
            "PC"
        ]
    },
    {
        "id": 3747,
        "name": "Metal Gear Solid V: Ground Zeroes",
        "genres": [
            {
                "id": 4,
                "name": "Action",
                "slug": "action",
                "games_count": 134093,
                "image_background": "https://media.rawg.io/media/games/c4b/c4b0cab189e73432de3a250d8cf1c84e.jpg"
            },
            {
                "id": 2,
                "name": "Shooter",
                "slug": "shooter",
                "games_count": 45301,
                "image_background": "https://media.rawg.io/media/games/7a2/7a2500ee8b2c0e1ff268bb4479463dea.jpg"
            }
        ],
        "image": "Metal_Gear_Solid_V_Ground_Zeroes.jpg",
        "rating": 3.9,
        "platforms": [
            "PlayStation 3",
            "PlayStation 4",
            "PC",
            "Xbox One",
            "Xbox 360"
        ]
    },
    {
        "id": 11935,
        "name": "Half-Life Deathmatch: Source",
        "genres": [
            {
                "id": 4,
                "name": "Action",
                "slug": "action",
                "games_count": 134093,
                "image_background": "https://media.rawg.io/media/games/c4b/c4b0cab189e73432de3a250d8cf1c84e.jpg"
            }
        ],
        "image": "Half_Life_Deathmatch_Source.jpg",
        "rating": 3.26,
        "platforms": [
            "macOS",
            "Linux",
            "PC"
        ]
    },
    {
        "id": 12536,
        "name": "Hellblade: Senua's Sacrifice",
        "genres": [
            {
                "id": 4,
                "name": "Action",
                "slug": "action",
                "games_count": 134093,
                "image_background": "https://media.rawg.io/media/games/c4b/c4b0cab189e73432de3a250d8cf1c84e.jpg"
            },
            {
                "id": 3,
                "name": "Adventure",
                "slug": "adventure",
                "games_count": 99466,
                "image_background": "https://media.rawg.io/media/games/26d/26d4437715bee60138dab4a7c8c59c92.jpg"
            },
            {
                "id": 51,
                "name": "Indie",
                "slug": "indie",
                "games_count": 40791,
                "image_background": "https://media.rawg.io/media/games/dd5/dd50d4266915d56dd5b63ae1bf72606a.jpg"
            }
        ],
        "image": "Hellblade_Senua_Sacrifice.jpg",
        "rating": 4.28,
        "platforms": [
            "PC",
            "Xbox One",
            "Nintendo Switch",
            "PlayStation 4"
        ]
    },
    {
        "id": 5563,
        "name": "Fallout: New Vegas",
        "genres": [
            {
                "id": 4,
                "name": "Action",
                "slug": "action",
                "games_count": 134093,
                "image_background": "https://media.rawg.io/media/games/c4b/c4b0cab189e73432de3a250d8cf1c84e.jpg"
            },
            {
                "id": 2,
                "name": "Shooter",
                "slug": "shooter",
                "games_count": 45301,
                "image_background": "https://media.rawg.io/media/games/7a2/7a2500ee8b2c0e1ff268bb4479463dea.jpg"
            },
            {
                "id": 3,
                "name": "Adventure",
                "slug": "adventure",
                "games_count": 99466,
                "image_background": "https://media.rawg.io/media/games/26d/26d4437715bee60138dab4a7c8c59c92.jpg"
            },
            {
                "id": 5,
                "name": "RPG",
                "slug": "role-playing-games-rpg",
                "games_count": 40860,
                "image_background": "https://media.rawg.io/media/games/d82/d82990b9c67ba0d2d09d4e6fa88885a7.jpg"
            }
        ],
        "image": "Fallout_New_Vegas.jpg",
        "rating": 4.42,
        "platforms": [
            "Xbox One",
            "PlayStation 4",
            "PlayStation 3",
            "PC",
            "Xbox 360"
        ]
    },
    {
        "id": 613,
        "name": "Bastion",
        "genres": [
            {
                "id": 4,
                "name": "Action",
                "slug": "action",
                "games_count": 134093,
                "image_background": "https://media.rawg.io/media/games/c4b/c4b0cab189e73432de3a250d8cf1c84e.jpg"
            },
            {
                "id": 3,
                "name": "Adventure",
                "slug": "adventure",
                "games_count": 99466,
                "image_background": "https://media.rawg.io/media/games/26d/26d4437715bee60138dab4a7c8c59c92.jpg"
            },
            {
                "id": 5,
                "name": "RPG",
                "slug": "role-playing-games-rpg",
                "games_count": 40860,
                "image_background": "https://media.rawg.io/media/games/d82/d82990b9c67ba0d2d09d4e6fa88885a7.jpg"
            },
            {
                "id": 51,
                "name": "Indie",
                "slug": "indie",
                "games_count": 40791,
                "image_background": "https://media.rawg.io/media/games/dd5/dd50d4266915d56dd5b63ae1bf72606a.jpg"
            }
        ],
        "image": "Bastion.jpg",
        "rating": 4.18,
        "platforms": [
            "PlayStation 4",
            "PS Vita",
            "Xbox One",
            "PC",
            "iOS",
            "Linux",
            "Nintendo Switch",
            "Xbox 360",
            "macOS"
        ]
    },
    {
        "id": 3543,
        "name": "Borderlands: The Pre-Sequel",
        "genres": [
            {
                "id": 4,
                "name": "Action",
                "slug": "action",
                "games_count": 134093,
                "image_background": "https://media.rawg.io/media/games/c4b/c4b0cab189e73432de3a250d8cf1c84e.jpg"
            },
            {
                "id": 2,
                "name": "Shooter",
                "slug": "shooter",
                "games_count": 45301,
                "image_background": "https://media.rawg.io/media/games/7a2/7a2500ee8b2c0e1ff268bb4479463dea.jpg"
            },
            {
                "id": 5,
                "name": "RPG",
                "slug": "role-playing-games-rpg",
                "games_count": 40860,
                "image_background": "https://media.rawg.io/media/games/d82/d82990b9c67ba0d2d09d4e6fa88885a7.jpg"
            }
        ],
        "image": "Borderlands_The_Pre_Sequel.jpg",
        "rating": 3.55,
        "platforms": [
            "PlayStation 3",
            "Xbox 360",
            "PlayStation 4",
            "Nintendo Switch",
            "PC",
            "Linux",
            "Android",
            "macOS"
        ]
    },
    {
        "id": 3017,
        "name": "Just Cause 3",
        "genres": [
            {
                "id": 4,
                "name": "Action",
                "slug": "action",
                "games_count": 134093,
                "image_background": "https://media.rawg.io/media/games/c4b/c4b0cab189e73432de3a250d8cf1c84e.jpg"
            },
            {
                "id": 2,
                "name": "Shooter",
                "slug": "shooter",
                "games_count": 45301,
                "image_background": "https://media.rawg.io/media/games/7a2/7a2500ee8b2c0e1ff268bb4479463dea.jpg"
            }
        ],
        "image": "Just_Cause_3.jpg",
        "rating": 3.35,
        "platforms": [
            "Xbox One",
            "PlayStation 4",
            "PC"
        ]
    },
    {
        "id": 3254,
        "name": "Journey",
        "genres": [
            {
                "id": 3,
                "name": "Adventure",
                "slug": "adventure",
                "games_count": 99466,
                "image_background": "https://media.rawg.io/media/games/26d/26d4437715bee60138dab4a7c8c59c92.jpg"
            },
            {
                "id": 19,
                "name": "Family",
                "slug": "family",
                "games_count": 5343,
                "image_background": "https://media.rawg.io/media/screenshots/157/1571cdfb52888191eabaf53c2b897240.jpg"
            },
            {
                "id": 51,
                "name": "Indie",
                "slug": "indie",
                "games_count": 40791,
                "image_background": "https://media.rawg.io/media/games/dd5/dd50d4266915d56dd5b63ae1bf72606a.jpg"
            }
        ],
        "image": "Journey.jpg",
        "rating": 4.33,
        "platforms": [
            "PlayStation 4",
            "PlayStation 3",
            "iOS",
            "PC"
        ]
    },
    {
        "id": 654,
        "name": "Stardew Valley",
        "genres": [
            {
                "id": 5,
                "name": "RPG",
                "slug": "role-playing-games-rpg",
                "games_count": 40860,
                "image_background": "https://media.rawg.io/media/games/d82/d82990b9c67ba0d2d09d4e6fa88885a7.jpg"
            },
            {
                "id": 14,
                "name": "Simulation",
                "slug": "simulation",
                "games_count": 51730,
                "image_background": "https://media.rawg.io/media/games/651/651ae84f2d5e36206aad90976a453329.jpg"
            },
            {
                "id": 51,
                "name": "Indie",
                "slug": "indie",
                "games_count": 40791,
                "image_background": "https://media.rawg.io/media/games/dd5/dd50d4266915d56dd5b63ae1bf72606a.jpg"
            }
        ],
        "image": "Stardew_Valley.jpg",
        "rating": 4.4,
        "platforms": [
            "Android",
            "PS Vita",
            "PlayStation 4",
            "Linux",
            "macOS",
            "iOS",
            "Nintendo Switch",
            "Xbox One",
            "PC"
        ]
    },
    {
        "id": 108,
        "name": "Mortal Kombat X",
        "genres": [
            {
                "id": 4,
                "name": "Action",
                "slug": "action",
                "games_count": 134093,
                "image_background": "https://media.rawg.io/media/games/c4b/c4b0cab189e73432de3a250d8cf1c84e.jpg"
            },
            {
                "id": 6,
                "name": "Fighting",
                "slug": "fighting",
                "games_count": 8662,
                "image_background": "https://media.rawg.io/media/games/9f3/9f3c513b301d8d7250a64dd7e73c62df.jpg"
            }
        ],
        "image": "Mortal_Kombat_X.jpg",
        "rating": 3.87,
        "platforms": [
            "Xbox One",
            "iOS",
            "PlayStation 4",
            "Android",
            "PC"
        ]
    },
    {
        "id": 13910,
        "name": "XCOM: Enemy Unknown",
        "genres": [
            {
                "id": 10,
                "name": "Strategy",
                "slug": "strategy",
                "games_count": 41420,
                "image_background": "https://media.rawg.io/media/games/651/651ae84f2d5e36206aad90976a453329.jpg"
            }
        ],
        "image": "XCOM_Enemy_Unknown.jpg",
        "rating": 4.19,
        "platforms": [
            "PC",
            "Android",
            "iOS",
            "Xbox 360",
            "PlayStation 3",
            "macOS"
        ]
    },
    {
        "id": 12447,
        "name": "The Elder Scrolls V: Skyrim Special Edition",
        "genres": [
            {
                "id": 4,
                "name": "Action",
                "slug": "action",
                "games_count": 134093,
                "image_background": "https://media.rawg.io/media/games/c4b/c4b0cab189e73432de3a250d8cf1c84e.jpg"
            },
            {
                "id": 5,
                "name": "RPG",
                "slug": "role-playing-games-rpg",
                "games_count": 40860,
                "image_background": "https://media.rawg.io/media/games/d82/d82990b9c67ba0d2d09d4e6fa88885a7.jpg"
            }
        ],
        "image": "The_Elder_Scrolls_V_Skyrim_Special_Edition.jpg",
        "rating": 4.46,
        "platforms": [
            "PC",
            "Xbox One",
            "PlayStation 4"
        ]
    },
    {
        "id": 5525,
        "name": "Brutal Legend",
        "genres": [
            {
                "id": 4,
                "name": "Action",
                "slug": "action",
                "games_count": 134093,
                "image_background": "https://media.rawg.io/media/games/c4b/c4b0cab189e73432de3a250d8cf1c84e.jpg"
            },
            {
                "id": 10,
                "name": "Strategy",
                "slug": "strategy",
                "games_count": 41420,
                "image_background": "https://media.rawg.io/media/games/651/651ae84f2d5e36206aad90976a453329.jpg"
            }
        ],
        "image": "Brutal_Legend.jpg",
        "rating": 3.66,
        "platforms": [
            "Xbox 360",
            "PlayStation 3",
            "Xbox One",
            "iOS",
            "PC",
            "Linux",
            "macOS"
        ]
    },
    {
        "id": 11934,
        "name": "Counter-Strike: Source",
        "genres": [
            {
                "id": 2,
                "name": "Shooter",
                "slug": "shooter",
                "games_count": 45301,
                "image_background": "https://media.rawg.io/media/games/7a2/7a2500ee8b2c0e1ff268bb4479463dea.jpg"
            }
        ],
        "image": "Counter_Strike_Source.jpg",
        "rating": 3.73,
        "platforms": [
            "macOS",
            "PC",
            "Linux"
        ]
    },
    {
        "id": 4513,
        "name": "Just Cause 2",
        "genres": [
            {
                "id": 4,
                "name": "Action",
                "slug": "action",
                "games_count": 134093,
                "image_background": "https://media.rawg.io/media/games/c4b/c4b0cab189e73432de3a250d8cf1c84e.jpg"
            },
            {
                "id": 2,
                "name": "Shooter",
                "slug": "shooter",
                "games_count": 45301,
                "image_background": "https://media.rawg.io/media/games/7a2/7a2500ee8b2c0e1ff268bb4479463dea.jpg"
            }
        ],
        "image": "Just_Cause_2.jpg",
        "rating": 3.59,
        "platforms": [
            "Xbox 360",
            "PlayStation 3",
            "Xbox One",
            "PC"
        ]
    },
    {
        "id": 3191,
        "name": "Mad Max",
        "genres": [
            {
                "id": 4,
                "name": "Action",
                "slug": "action",
                "games_count": 134093,
                "image_background": "https://media.rawg.io/media/games/c4b/c4b0cab189e73432de3a250d8cf1c84e.jpg"
            },
            {
                "id": 3,
                "name": "Adventure",
                "slug": "adventure",
                "games_count": 99466,
                "image_background": "https://media.rawg.io/media/games/26d/26d4437715bee60138dab4a7c8c59c92.jpg"
            }
        ],
        "image": "Mad_Max.jpg",
        "rating": 3.74,
        "platforms": [
            "PC",
            "Xbox One",
            "PlayStation 4",
            "Xbox 360",
            "Linux",
            "macOS"
        ]
    },
    {
        "id": 9882,
        "name": "Don't Starve Together",
        "genres": [
            {
                "id": 4,
                "name": "Action",
                "slug": "action",
                "games_count": 134093,
                "image_background": "https://media.rawg.io/media/games/c4b/c4b0cab189e73432de3a250d8cf1c84e.jpg"
            },
            {
                "id": 14,
                "name": "Simulation",
                "slug": "simulation",
                "games_count": 51730,
                "image_background": "https://media.rawg.io/media/games/651/651ae84f2d5e36206aad90976a453329.jpg"
            },
            {
                "id": 51,
                "name": "Indie",
                "slug": "indie",
                "games_count": 40791,
                "image_background": "https://media.rawg.io/media/games/dd5/dd50d4266915d56dd5b63ae1bf72606a.jpg"
            }
        ],
        "image": "Dont_Starve_Together.jpg",
        "rating": 3.79,
        "platforms": [
            "Linux",
            "Xbox One",
            "PlayStation 4",
            "macOS",
            "PC"
        ]
    },
    {
        "id": 50738,
        "name": "Death Stranding",
        "genres": [
            {
                "id": 4,
                "name": "Action",
                "slug": "action",
                "games_count": 134093,
                "image_background": "https://media.rawg.io/media/games/c4b/c4b0cab189e73432de3a250d8cf1c84e.jpg"
            },
            {
                "id": 3,
                "name": "Adventure",
                "slug": "adventure",
                "games_count": 99466,
                "image_background": "https://media.rawg.io/media/games/26d/26d4437715bee60138dab4a7c8c59c92.jpg"
            }
        ],
        "image": "Death_Stranding.jpg",
        "rating": 4.36,
        "platforms": [
            "PlayStation 4",
            "PC"
        ]
    },
    {
        "id": 864,
        "name": "Dishonored 2",
        "genres": [
            {
                "id": 4,
                "name": "Action",
                "slug": "action",
                "games_count": 134093,
                "image_background": "https://media.rawg.io/media/games/c4b/c4b0cab189e73432de3a250d8cf1c84e.jpg"
            },
            {
                "id": 5,
                "name": "RPG",
                "slug": "role-playing-games-rpg",
                "games_count": 40860,
                "image_background": "https://media.rawg.io/media/games/d82/d82990b9c67ba0d2d09d4e6fa88885a7.jpg"
            }
        ],
        "image": "Dishonored_2.jpg",
        "rating": 4.26,
        "platforms": [
            "PC",
            "Xbox One",
            "PlayStation 4"
        ]
    }
]